{
  "Scope": "Descriptive runtime evidence for this recorded Windows development machine only.",
  "RepositoryRevision": "0bdc68f0b9353e38ef8970c9bb699dad1913ca09",
  "Scales": [
    {
      "Scale": 64,
      "FirstCorrectFrame": {
        "FreshReleaseRuns": 10,
        "Samples": [
          {
            "SourceRevision": "1",
            "DerivationMilliseconds": 755.5119,
            "UploadInstallMilliseconds": 2.7486000000000104,
            "PresentationMilliseconds": 0.7793000000000347,
            "TotalMilliseconds": 759.0398,
            "Resources": {
              "occupied_voxels": 52608,
              "exposed_quads": 13616,
              "vertices": 54464,
              "indices": 81696,
              "draw_calls": 1,
              "cpu_artifact_bytes": 2505344,
              "gpu_buffer_bytes": 2505344
            },
            "RawFile": "first-correct-frame-64-01.jsonl"
          },
          {
            "SourceRevision": "1",
            "DerivationMilliseconds": 525.1206000000001,
            "UploadInstallMilliseconds": 2.1423999999999523,
            "PresentationMilliseconds": 0.7153999999999314,
            "TotalMilliseconds": 527.9784,
            "Resources": {
              "occupied_voxels": 52608,
              "exposed_quads": 13616,
              "vertices": 54464,
              "indices": 81696,
              "draw_calls": 1,
              "cpu_artifact_bytes": 2505344,
              "gpu_buffer_bytes": 2505344
            },
            "RawFile": "first-correct-frame-64-02.jsonl"
          },
          {
            "SourceRevision": "1",
            "DerivationMilliseconds": 569.5572,
            "UploadInstallMilliseconds": 20.139099999999985,
            "PresentationMilliseconds": 3.3957000000000335,
            "TotalMilliseconds": 593.092,
            "Resources": {
              "occupied_voxels": 52608,
              "exposed_quads": 13616,
              "vertices": 54464,
              "indices": 81696,
              "draw_calls": 1,
              "cpu_artifact_bytes": 2505344,
              "gpu_buffer_bytes": 2505344
            },
            "RawFile": "first-correct-frame-64-03.jsonl"
          },
          {
            "SourceRevision": "1",
            "DerivationMilliseconds": 531.8688000000001,
            "UploadInstallMilliseconds": 2.696499999999901,
            "PresentationMilliseconds": 0.6063000000000329,
            "TotalMilliseconds": 535.1716,
            "Resources": {
              "occupied_voxels": 52608,
              "exposed_quads": 13616,
              "vertices": 54464,
              "indices": 81696,
              "draw_calls": 1,
              "cpu_artifact_bytes": 2505344,
              "gpu_buffer_bytes": 2505344
            },
            "RawFile": "first-correct-frame-64-04.jsonl"
          },
          {
            "SourceRevision": "1",
            "DerivationMilliseconds": 591.5692,
            "UploadInstallMilliseconds": 2.581700000000069,
            "PresentationMilliseconds": 0.5592999999998938,
            "TotalMilliseconds": 594.7102,
            "Resources": {
              "occupied_voxels": 52608,
              "exposed_quads": 13616,
              "vertices": 54464,
              "indices": 81696,
              "draw_calls": 1,
              "cpu_artifact_bytes": 2505344,
              "gpu_buffer_bytes": 2505344
            },
            "RawFile": "first-correct-frame-64-05.jsonl"
          },
          {
            "SourceRevision": "1",
            "DerivationMilliseconds": 522.2792000000001,
            "UploadInstallMilliseconds": 2.3105999999999085,
            "PresentationMilliseconds": 0.7492000000000871,
            "TotalMilliseconds": 525.339,
            "Resources": {
              "occupied_voxels": 52608,
              "exposed_quads": 13616,
              "vertices": 54464,
              "indices": 81696,
              "draw_calls": 1,
              "cpu_artifact_bytes": 2505344,
              "gpu_buffer_bytes": 2505344
            },
            "RawFile": "first-correct-frame-64-06.jsonl"
          },
          {
            "SourceRevision": "1",
            "DerivationMilliseconds": 532.302,
            "UploadInstallMilliseconds": 2.902099999999905,
            "PresentationMilliseconds": 0.6835000000000946,
            "TotalMilliseconds": 535.8876,
            "Resources": {
              "occupied_voxels": 52608,
              "exposed_quads": 13616,
              "vertices": 54464,
              "indices": 81696,
              "draw_calls": 1,
              "cpu_artifact_bytes": 2505344,
              "gpu_buffer_bytes": 2505344
            },
            "RawFile": "first-correct-frame-64-07.jsonl"
          },
          {
            "SourceRevision": "1",
            "DerivationMilliseconds": 606.5128,
            "UploadInstallMilliseconds": 2.259800000000041,
            "PresentationMilliseconds": 0.6224999999999454,
            "TotalMilliseconds": 609.3951,
            "Resources": {
              "occupied_voxels": 52608,
              "exposed_quads": 13616,
              "vertices": 54464,
              "indices": 81696,
              "draw_calls": 1,
              "cpu_artifact_bytes": 2505344,
              "gpu_buffer_bytes": 2505344
            },
            "RawFile": "first-correct-frame-64-08.jsonl"
          },
          {
            "SourceRevision": "1",
            "DerivationMilliseconds": 534.0717000000001,
            "UploadInstallMilliseconds": 2.204499999999939,
            "PresentationMilliseconds": 0.5421000000000049,
            "TotalMilliseconds": 536.8183,
            "Resources": {
              "occupied_voxels": 52608,
              "exposed_quads": 13616,
              "vertices": 54464,
              "indices": 81696,
              "draw_calls": 1,
              "cpu_artifact_bytes": 2505344,
              "gpu_buffer_bytes": 2505344
            },
            "RawFile": "first-correct-frame-64-09.jsonl"
          },
          {
            "SourceRevision": "1",
            "DerivationMilliseconds": 499.9435,
            "UploadInstallMilliseconds": 1.591700000000003,
            "PresentationMilliseconds": 0.5955000000000723,
            "TotalMilliseconds": 502.13070000000005,
            "Resources": {
              "occupied_voxels": 52608,
              "exposed_quads": 13616,
              "vertices": 54464,
              "indices": 81696,
              "draw_calls": 1,
              "cpu_artifact_bytes": 2505344,
              "gpu_buffer_bytes": 2505344
            },
            "RawFile": "first-correct-frame-64-10.jsonl"
          }
        ],
        "Derivation": {
          "count": 10,
          "median": 533.18685,
          "p95": 755.5119,
          "maximum": 755.5119
        },
        "UploadInstall": {
          "count": 10,
          "median": 2.4461499999999887,
          "p95": 20.139099999999985,
          "maximum": 20.139099999999985
        },
        "Presentation": {
          "count": 10,
          "median": 0.65300000000002,
          "p95": 3.3957000000000335,
          "maximum": 3.3957000000000335
        },
        "Total": {
          "count": 10,
          "median": 536.35295,
          "p95": 759.0398,
          "maximum": 759.0398
        }
      },
      "CpuFrame": {
        "count": 109197,
        "median": 0.21,
        "p95": 0.29910000000000003,
        "maximum": 8.697899999999999
      },
      "GpuFrame": {
        "count": 109197,
        "median": 0.154848,
        "p95": 0.155456,
        "maximum": 0.19248
      }
    },
    {
      "Scale": 128,
      "FirstCorrectFrame": {
        "FreshReleaseRuns": 10,
        "Samples": [
          {
            "SourceRevision": "1",
            "DerivationMilliseconds": 523.9293,
            "UploadInstallMilliseconds": 3.1965000000000146,
            "PresentationMilliseconds": 0.6259000000000015,
            "TotalMilliseconds": 527.7517,
            "Resources": {
              "occupied_voxels": 420864,
              "exposed_quads": 54464,
              "vertices": 217856,
              "indices": 326784,
              "draw_calls": 1,
              "cpu_artifact_bytes": 10021376,
              "gpu_buffer_bytes": 10021376
            },
            "RawFile": "first-correct-frame-128-01.jsonl"
          },
          {
            "SourceRevision": "1",
            "DerivationMilliseconds": 490.5779,
            "UploadInstallMilliseconds": 1.995900000000006,
            "PresentationMilliseconds": 0.6052999999999997,
            "TotalMilliseconds": 493.1791,
            "Resources": {
              "occupied_voxels": 420864,
              "exposed_quads": 54464,
              "vertices": 217856,
              "indices": 326784,
              "draw_calls": 1,
              "cpu_artifact_bytes": 10021376,
              "gpu_buffer_bytes": 10021376
            },
            "RawFile": "first-correct-frame-128-02.jsonl"
          },
          {
            "SourceRevision": "1",
            "DerivationMilliseconds": 477.6529,
            "UploadInstallMilliseconds": 2.155200000000036,
            "PresentationMilliseconds": 0.6364999999999554,
            "TotalMilliseconds": 480.4446,
            "Resources": {
              "occupied_voxels": 420864,
              "exposed_quads": 54464,
              "vertices": 217856,
              "indices": 326784,
              "draw_calls": 1,
              "cpu_artifact_bytes": 10021376,
              "gpu_buffer_bytes": 10021376
            },
            "RawFile": "first-correct-frame-128-03.jsonl"
          },
          {
            "SourceRevision": "1",
            "DerivationMilliseconds": 512.8075,
            "UploadInstallMilliseconds": 2.1161999999999352,
            "PresentationMilliseconds": 0.8268000000000484,
            "TotalMilliseconds": 515.7505,
            "Resources": {
              "occupied_voxels": 420864,
              "exposed_quads": 54464,
              "vertices": 217856,
              "indices": 326784,
              "draw_calls": 1,
              "cpu_artifact_bytes": 10021376,
              "gpu_buffer_bytes": 10021376
            },
            "RawFile": "first-correct-frame-128-04.jsonl"
          },
          {
            "SourceRevision": "1",
            "DerivationMilliseconds": 458.3868,
            "UploadInstallMilliseconds": 2.310100000000034,
            "PresentationMilliseconds": 0.5885000000000105,
            "TotalMilliseconds": 461.28540000000004,
            "Resources": {
              "occupied_voxels": 420864,
              "exposed_quads": 54464,
              "vertices": 217856,
              "indices": 326784,
              "draw_calls": 1,
              "cpu_artifact_bytes": 10021376,
              "gpu_buffer_bytes": 10021376
            },
            "RawFile": "first-correct-frame-128-05.jsonl"
          },
          {
            "SourceRevision": "1",
            "DerivationMilliseconds": 538.3315,
            "UploadInstallMilliseconds": 2.5656999999999925,
            "PresentationMilliseconds": 0.6793999999999869,
            "TotalMilliseconds": 541.5766,
            "Resources": {
              "occupied_voxels": 420864,
              "exposed_quads": 54464,
              "vertices": 217856,
              "indices": 326784,
              "draw_calls": 1,
              "cpu_artifact_bytes": 10021376,
              "gpu_buffer_bytes": 10021376
            },
            "RawFile": "first-correct-frame-128-06.jsonl"
          },
          {
            "SourceRevision": "1",
            "DerivationMilliseconds": 509.6435,
            "UploadInstallMilliseconds": 2.703999999999951,
            "PresentationMilliseconds": 0.7241999999999962,
            "TotalMilliseconds": 513.0717,
            "Resources": {
              "occupied_voxels": 420864,
              "exposed_quads": 54464,
              "vertices": 217856,
              "indices": 326784,
              "draw_calls": 1,
              "cpu_artifact_bytes": 10021376,
              "gpu_buffer_bytes": 10021376
            },
            "RawFile": "first-correct-frame-128-07.jsonl"
          },
          {
            "SourceRevision": "1",
            "DerivationMilliseconds": 506.3544,
            "UploadInstallMilliseconds": 3.002200000000073,
            "PresentationMilliseconds": 0.6312999999999533,
            "TotalMilliseconds": 509.9879,
            "Resources": {
              "occupied_voxels": 420864,
              "exposed_quads": 54464,
              "vertices": 217856,
              "indices": 326784,
              "draw_calls": 1,
              "cpu_artifact_bytes": 10021376,
              "gpu_buffer_bytes": 10021376
            },
            "RawFile": "first-correct-frame-128-08.jsonl"
          },
          {
            "SourceRevision": "1",
            "DerivationMilliseconds": 489.5661,
            "UploadInstallMilliseconds": 2.3378000000000156,
            "PresentationMilliseconds": 0.7031999999999812,
            "TotalMilliseconds": 492.6071,
            "Resources": {
              "occupied_voxels": 420864,
              "exposed_quads": 54464,
              "vertices": 217856,
              "indices": 326784,
              "draw_calls": 1,
              "cpu_artifact_bytes": 10021376,
              "gpu_buffer_bytes": 10021376
            },
            "RawFile": "first-correct-frame-128-09.jsonl"
          },
          {
            "SourceRevision": "1",
            "DerivationMilliseconds": 489.3587,
            "UploadInstallMilliseconds": 2.7035999999999945,
            "PresentationMilliseconds": 0.5224999999999795,
            "TotalMilliseconds": 492.5848,
            "Resources": {
              "occupied_voxels": 420864,
              "exposed_quads": 54464,
              "vertices": 217856,
              "indices": 326784,
              "draw_calls": 1,
              "cpu_artifact_bytes": 10021376,
              "gpu_buffer_bytes": 10021376
            },
            "RawFile": "first-correct-frame-128-10.jsonl"
          }
        ],
        "Derivation": {
          "count": 10,
          "median": 498.46614999999997,
          "p95": 538.3315,
          "maximum": 538.3315
        },
        "UploadInstall": {
          "count": 10,
          "median": 2.451750000000004,
          "p95": 3.1965000000000146,
          "maximum": 3.1965000000000146
        },
        "Presentation": {
          "count": 10,
          "median": 0.6338999999999544,
          "p95": 0.8268000000000484,
          "maximum": 0.8268000000000484
        },
        "Total": {
          "count": 10,
          "median": 501.5835,
          "p95": 541.5766,
          "maximum": 541.5766
        }
      },
      "CpuFrame": {
        "count": 41221,
        "median": 0.6491,
        "p95": 0.8479,
        "maximum": 6.8059
      },
      "GpuFrame": {
        "count": 41221,
        "median": 0.590944,
        "p95": 0.593632,
        "maximum": 5.42288
      }
    },
    {
      "Scale": 256,
      "FirstCorrectFrame": {
        "FreshReleaseRuns": 10,
        "Samples": [
          {
            "SourceRevision": "1",
            "DerivationMilliseconds": 684.4824000000001,
            "UploadInstallMilliseconds": 7.197399999999902,
            "PresentationMilliseconds": 0.7027000000000498,
            "TotalMilliseconds": 692.3825,
            "Resources": {
              "occupied_voxels": 3366912,
              "exposed_quads": 217856,
              "vertices": 871424,
              "indices": 1307136,
              "draw_calls": 1,
              "cpu_artifact_bytes": 40085504,
              "gpu_buffer_bytes": 40085504
            },
            "RawFile": "first-correct-frame-256-01.jsonl"
          },
          {
            "SourceRevision": "1",
            "DerivationMilliseconds": 676.5369,
            "UploadInstallMilliseconds": 6.223400000000083,
            "PresentationMilliseconds": 0.6565999999999121,
            "TotalMilliseconds": 683.4168999999999,
            "Resources": {
              "occupied_voxels": 3366912,
              "exposed_quads": 217856,
              "vertices": 871424,
              "indices": 1307136,
              "draw_calls": 1,
              "cpu_artifact_bytes": 40085504,
              "gpu_buffer_bytes": 40085504
            },
            "RawFile": "first-correct-frame-256-02.jsonl"
          },
          {
            "SourceRevision": "1",
            "DerivationMilliseconds": 682.7237,
            "UploadInstallMilliseconds": 4.502900000000068,
            "PresentationMilliseconds": 0.6820999999999913,
            "TotalMilliseconds": 687.9087000000001,
            "Resources": {
              "occupied_voxels": 3366912,
              "exposed_quads": 217856,
              "vertices": 871424,
              "indices": 1307136,
              "draw_calls": 1,
              "cpu_artifact_bytes": 40085504,
              "gpu_buffer_bytes": 40085504
            },
            "RawFile": "first-correct-frame-256-03.jsonl"
          },
          {
            "SourceRevision": "1",
            "DerivationMilliseconds": 669.6998,
            "UploadInstallMilliseconds": 5.6825000000000045,
            "PresentationMilliseconds": 0.5339000000000169,
            "TotalMilliseconds": 675.9162,
            "Resources": {
              "occupied_voxels": 3366912,
              "exposed_quads": 217856,
              "vertices": 871424,
              "indices": 1307136,
              "draw_calls": 1,
              "cpu_artifact_bytes": 40085504,
              "gpu_buffer_bytes": 40085504
            },
            "RawFile": "first-correct-frame-256-04.jsonl"
          },
          {
            "SourceRevision": "1",
            "DerivationMilliseconds": 698.403,
            "UploadInstallMilliseconds": 5.863599999999906,
            "PresentationMilliseconds": 0.651700000000119,
            "TotalMilliseconds": 704.9183,
            "Resources": {
              "occupied_voxels": 3366912,
              "exposed_quads": 217856,
              "vertices": 871424,
              "indices": 1307136,
              "draw_calls": 1,
              "cpu_artifact_bytes": 40085504,
              "gpu_buffer_bytes": 40085504
            },
            "RawFile": "first-correct-frame-256-05.jsonl"
          },
          {
            "SourceRevision": "1",
            "DerivationMilliseconds": 715.1125000000001,
            "UploadInstallMilliseconds": 6.650499999999965,
            "PresentationMilliseconds": 0.6957999999999629,
            "TotalMilliseconds": 722.4588,
            "Resources": {
              "occupied_voxels": 3366912,
              "exposed_quads": 217856,
              "vertices": 871424,
              "indices": 1307136,
              "draw_calls": 1,
              "cpu_artifact_bytes": 40085504,
              "gpu_buffer_bytes": 40085504
            },
            "RawFile": "first-correct-frame-256-06.jsonl"
          },
          {
            "SourceRevision": "1",
            "DerivationMilliseconds": 701.5215999999999,
            "UploadInstallMilliseconds": 4.770200000000159,
            "PresentationMilliseconds": 0.6749999999999545,
            "TotalMilliseconds": 706.9668,
            "Resources": {
              "occupied_voxels": 3366912,
              "exposed_quads": 217856,
              "vertices": 871424,
              "indices": 1307136,
              "draw_calls": 1,
              "cpu_artifact_bytes": 40085504,
              "gpu_buffer_bytes": 40085504
            },
            "RawFile": "first-correct-frame-256-07.jsonl"
          },
          {
            "SourceRevision": "1",
            "DerivationMilliseconds": 670.9209999999999,
            "UploadInstallMilliseconds": 7.674100000000067,
            "PresentationMilliseconds": 0.6693000000000211,
            "TotalMilliseconds": 679.2644,
            "Resources": {
              "occupied_voxels": 3366912,
              "exposed_quads": 217856,
              "vertices": 871424,
              "indices": 1307136,
              "draw_calls": 1,
              "cpu_artifact_bytes": 40085504,
              "gpu_buffer_bytes": 40085504
            },
            "RawFile": "first-correct-frame-256-08.jsonl"
          },
          {
            "SourceRevision": "1",
            "DerivationMilliseconds": 677.1644,
            "UploadInstallMilliseconds": 8.210299999999961,
            "PresentationMilliseconds": 0.7733000000000629,
            "TotalMilliseconds": 686.148,
            "Resources": {
              "occupied_voxels": 3366912,
              "exposed_quads": 217856,
              "vertices": 871424,
              "indices": 1307136,
              "draw_calls": 1,
              "cpu_artifact_bytes": 40085504,
              "gpu_buffer_bytes": 40085504
            },
            "RawFile": "first-correct-frame-256-09.jsonl"
          },
          {
            "SourceRevision": "1",
            "DerivationMilliseconds": 677.6668999999999,
            "UploadInstallMilliseconds": 8.16800000000012,
            "PresentationMilliseconds": 0.7058999999999287,
            "TotalMilliseconds": 686.5408,
            "Resources": {
              "occupied_voxels": 3366912,
              "exposed_quads": 217856,
              "vertices": 871424,
              "indices": 1307136,
              "draw_calls": 1,
              "cpu_artifact_bytes": 40085504,
              "gpu_buffer_bytes": 40085504
            },
            "RawFile": "first-correct-frame-256-10.jsonl"
          }
        ],
        "Derivation": {
          "count": 10,
          "median": 680.1953,
          "p95": 715.1125000000001,
          "maximum": 715.1125000000001
        },
        "UploadInstall": {
          "count": 10,
          "median": 6.436950000000024,
          "p95": 8.210299999999961,
          "maximum": 8.210299999999961
        },
        "Presentation": {
          "count": 10,
          "median": 0.6785499999999729,
          "p95": 0.7733000000000629,
          "maximum": 0.7733000000000629
        },
        "Total": {
          "count": 10,
          "median": 687.2247500000001,
          "p95": 722.4588,
          "maximum": 722.4588
        }
      },
      "CpuFrame": {
        "count": 11214,
        "median": 2.4329,
        "p95": 3.4518,
        "maximum": 29.828899999999997
      },
      "GpuFrame": {
        "count": 11214,
        "median": 2.352384,
        "p95": 3.348352,
        "maximum": 10.47712
      }
    }
  ]
}
